cloudbuddy/__init__.py
cloudbuddy/aws_env.py
cloudbuddy/config.py
cloudbuddy/constants.py
cloudbuddy/main.py
cloudbuddy/prettify_message.py
cloudbuddy/aws_resources/__init__.py
cloudbuddy/aws_resources/ecs_resource.py
cloudbuddy/aws_resources/elb_resource.py
cloudbuddy/aws_resources/r53_resource.py
cloudbuddy/aws_resources/rds_resource.py
cloudbuddy/aws_resources/resource_base.py
cloudbuddy/aws_resources/vpc_resource.py
cloudbuddy/infra/__init__.py
cloudbuddy/infra/ecr_infra.py
cloudbuddy/infra/ecs_infra.py
cloudbuddy/infra/elb_infra.py
cloudbuddy/infra/r53_infra.py
cloudbuddy/infra/rds_infra.py
cloudbuddy/infra/vpc_infra.py
cloudbuddy-0.0.2.dist-info/LICENSE.txt
cloudbuddy-0.0.2.dist-info/METADATA
cloudbuddy-0.0.2.dist-info/WHEEL
cloudbuddy-0.0.2.dist-info/entry_points.txt
cloudbuddy-0.0.2.dist-info/top_level.txt
cloudbuddy-0.0.2.dist-info/RECORD
