Metadata-Version: 2.1
Name: cloudbuddy
Version: 0.0.2
Summary: AWS Infrastructure automation
Home-page: UNKNOWN
Author: Seneca Global
Author-email: saiphani.alapati@senecaglobal.com
License: Copyright (c) 2022 senecaglobal.com
Keywords: python,aws,automation,ecs,ecr,rds
Platform: UNKNOWN
Classifier: Development Status :: 1 - Planning
Classifier: Intended Audience :: Developers
Classifier: Programming Language :: Python :: 3
Classifier: Operating System :: Unix
Classifier: Operating System :: MacOS :: MacOS X
Classifier: Operating System :: Microsoft :: Windows
License-File: LICENSE.txt
Requires-Dist: boto3
Requires-Dist: botocore
Requires-Dist: colorama
Requires-Dist: python-dotenv
Requires-Dist: PyYAML
Requires-Dist: pytest
